{"apikey":"ydfJwEXee","action":"record.json","success":true,"statsDuration":943,"requestNumber":2152,"object":{"type":"IMAGE","title":["Painting (Spanish Dancer)","Painting"],"about":"/08502/97F98E7A5794C3244593221DE9A7CF8CC72BD916","proxies":[{"about":"/proxy/provider/08502/97F98E7A5794C3244593221DE9A7CF8CC72BD916","dcCreator":{"def":["Joan Miró, Spanish, 1893–1983 [Create]","Spanish, 1893–1983 [Create]"]},"dcDescription":{"def":["In this witty, fanciful painting, Surrealist Joan Miró combines vivid symbols of Spanish dance—a colorful mantilla, a flared skirt, and a pointed shoe—to convey the rhythm and subtle provocativeness of the dancer. Floating in a cloudlike white patch, a bull-like creature composed of fish- and foxlike elements recalls similar animal forms in Miró's fantastical menagerie. Subverting conventional technique, the artist leaves the majority of the canvas bare, using the white pigment to represent perhaps the dancer's skirt and to emphasize the surface of the painting. Miró's fascination with Spanish dancers was manifest in at least nine works produced in Paris between 1921 and 1929. They draw on symbols and imagery recurrent in his oeuvre, yet they are rendered in a profusion of artistic styles, from Realism and Cubism to Surrealism and abstract collage. One of them, Spanish Dancer (1924), also in the Museum's collection, conveys a dancer's spinning movement and costume through a simple, geometric, steplike line and spiraling red dotted line. In his paintings of Spanish dancers, Miró evoked traditional Catalonian art forms. After World War I, the Catalonia of Miró's youth was transformed by political change and class conflict. Reacting against the prevailing militant nationalism, Miró hoped to introduce into modern Catalonia a cultural basis for civic unity. Inspired by Spanish dolls, Catalan figures, and folk art, with which he surrounded himself during his self-imposed exile in Paris, Miró was making reference to the timeless, bucolic landscape of his childhood.","Repository/Location: Israel Museum, Jerusalem"]},"dcIdentifier":{"def":["local (default) B03.0825","item 202227 [Metadata]"]},"dcRights":{"def":["Gift of Sylvia and Joseph Slifka, New York, to American Friends of the Israel Museum","Israel Museum, Jerusalem","Photo © The Israel Museum, Jerusalem [Resource]","© ADAGP, Paris, 2007 [Resource]"]},"dcSubject":{"def":["Automatism","Painting","Modern Art","Art"]},"dcTitle":{"def":["Painting (Spanish Dancer)","Painting"]},"dctermsCreated":{"def":["1927 [Create]"]},"dctermsExtent":{"def":["146 x 114 cm"]},"dctermsMedium":{"def":["Oil on canvas"]},"proxyIn":["/aggregation/provider/08502/97F98E7A5794C3244593221DE9A7CF8CC72BD916"],"proxyFor":"/item/08502/97F98E7A5794C3244593221DE9A7CF8CC72BD916","edmType":"IMAGE","europeanaProxy":false},{"about":"/proxy/europeana/08502/97F98E7A5794C3244593221DE9A7CF8CC72BD916","proxyIn":["/aggregation/europeana/08502/97F98E7A5794C3244593221DE9A7CF8CC72BD916"],"proxyFor":"/item/08502/97F98E7A5794C3244593221DE9A7CF8CC72BD916","year":{"def":["1927"]},"europeanaProxy":true}],"aggregations":[{"about":"/aggregation/provider/08502/97F98E7A5794C3244593221DE9A7CF8CC72BD916","edmDataProvider":{"def":["Israel Museum, Jerusalem"]},"edmIsShownAt":"http://www.imj.org.il/imagine/collections/item.asp?itemNum=202227&bt=europeanaapi","edmObject":"http://www.imj.org.il/images/corridor/bezalel/imj book 2005/miro, joan, painting- spanish dancer, 1927.jpg","edmProvider":{"def":["Athena"]},"webResources":[{"about":"http://www.imj.org.il/imagine/collections/item.asp?itemNum=202227"},{"about":"http://www.imj.org.il/images/corridor/bezalel/imj book 2005/miro, joan, painting- spanish dancer, 1927.jpg"}]}],"concepts":[{"about":"http://www.eionet.europa.eu/gemet/concept/568","prefLabel":{"def":["vrouw","land (natur)","no","femeie","mulher","nainen","espèce","γη/ξηρά/έκταση/αγρός/έδαφος/κτήμα","物种, 种","woman","arte","искусство","виды","umetnost","menas","rūšys","arter","art","kvinne","land; mark","territorio (geografia)","kvinna","土地","faj","kunst","видове","art (spezies)","pozemek","vrsta","especies","pays","művészet","艺术","föld","mujer","liik\n        (biol)","donna","art (biologi)","espécies","sztuka","ženska","femme","gatunek","land","maa","женщина","земля","ląd","taide","изкуство","τέχνη/καλλιτεχνικά","žemė, sausuma","terras","moteris","teritoriu","tierra","είδος","umenie","druh","γυναίκα","laji","kvinde","zemlja, površje, zemljišče","artă","species","女子","žena","naine","жена","земя","umění","konst","frau","kobieta","zem","specie","soort"]},"broader":["http://www.eionet.europa.eu/gemet/concept/4056","http://www.eionet.europa.eu/gemet/concept/5524","http://www.eionet.europa.eu/gemet/concept/2470","http://www.eionet.europa.eu/gemet/concept/2060","http://www.eionet.europa.eu/gemet/concept/6527","http://www.eionet.europa.eu/gemet/concept/1921","http://www.eionet.europa.eu/gemet/concept/1912","http://www.eionet.europa.eu/gemet/concept/4805","http://www.eionet.europa.eu/gemet/concept/7472","http://www.eionet.europa.eu/gemet/concept/2457","videnskab","mokslas apie gyvybę","naturvidenskab","prírodné vedy","cultural heritage","parametr ekologiczny","struttura della popolazione","parametro ecologico","vede o živih organizmih, biološke vede","ekologie","kultura [společnost]","demografía","ekologia","ekologi","cultura (socialização)","luonnontieteet","vedy","ökoloogia","démographie","демография","patrimonio culturale","parametr ekologický","人口统计","население","žmonių populiacija","生态学","természettudomány","økologisk parameter","biowissenschaften","ştiinţă naturală","bevölkerung","structură a populaţiei","parámetro ecológico","ciencia","βιολογικές επιστήμες","scienze della vita","ecologische parameter","ecologia","bioloogia, teadus elust","естественная наука","kultúra (spoločenstvo)","ecologie","población humana","ekologinen parametri","nauka","dědictví kulturní","populace lidská","ľudská populácia","nauki przyrodnicze","gamtos mokslas","自然科学","népességszerkezet","ανθρώπινος πληθυσμός","økologi","biologické vedy","ciencias naturales","култура (на обществото)","ökologischer parameter","patrimoniu cultural","science","biovitenskap","estrutura da população","demografi","naturvitenskap","scienze naturali","культурное наследие","life science","наука за живота","popolazione umana","ekológia","население (на хора)","kultur","kultura","élettel foglalkozó tudomány","ekologija","dziedzictwo kulturowe","prebivalci, prebivalstvo","znanost, veda","kulturális örökség","kulturarv","ecología","tudomány","екология","επιστήμη","科学","ludność","befolkning","štruktúra populácie","cultureel erfgoed","ökoloogiline näitaja","gyventojų sudėtis","demografija","kulturna dediščina","population","ekološki parameter","культура (общество)","parametru ecologic","ökológia","kultūros paveldas","ciências naturais","ekologinis parametras","οικολογική παράμετρος","ştiinţele vieţii","kultuur","bevölkerungsstruktur","ecological parameter","levenswetenschappen","cultură (societate)","ökologie","biologiset tieteet","parâmetros ecológicos","人类种群","demografia","экология","demografie","emberi populáció","науки о жизни","ökológiai paraméter","naturwissenschaft","生命科学","teadus","文化（社会）","kultúra (társadalom)","kultura, civilizacija (družb)","patrimoine culturel","natural science","natuurwetenschappen","structure de la population","kultur (samfund)","população humana","biovetenskaper","rahvastiku struktuur","структура населения","patrimonio cultural","demograafia, rahvastikuteadus","cultura","wissenschaft","demography","tiede","ekologický parameter","kultúrne dedičstvo","väestö","ciências da vida","naravoslovje","population structure","demográfia","bevolking","ekologisk parameter","οικολογία","biovidenskaber","vědy přírodní","sciences naturelles","ciência","наука","património cultural","културно наследство","人口结构","biologie","vitenskap","struktura ludnościowa","inimpopulatsioon","екологичен параметър","milieu","sciences de la vie","структура на населението","πολιτιστική κληρονομιά","kulttuuri, sivistys","struktura prebivalstva","естествени науки/естествознание","écologie","väestötiede","paramètre écologique","kulttuuriperintö","przyrodoznawstwo","bevolkingsstructuur","φυσικές επιστήμες","vetenskap","scienze","πολιτισμός/ (πνευματική) καλλιέργεια/παιδεία/κουλτούρα","kultuuripärand","věda","beschaving","διάρθρωση του πληθυσμού","kulturerbe","väestörakenne","struktura obyvatelstva","ştiinţă","populaţie umană","ecology","ciencias de la vida","culture (aspects sociaux)","kultūra (visuomenė)","estructura de la población","culture (society)","naturvetenskap","文化遗产","befolkningsstruktur","δημογραφία","生态参数","loodusteadus","demographie","mokslas","human population","экологический параметр","wetenschappen"]}],"europeanaCompleteness":10,"providedCHOs":[{"about":"/item/08502/97F98E7A5794C3244593221DE9A7CF8CC72BD916"}],"europeanaAggregation":{"about":"/aggregation/europeana/08502/97F98E7A5794C3244593221DE9A7CF8CC72BD916","edmLandingPage":"http://www.europeana.eu/portal/record/08502/97F98E7A5794C3244593221DE9A7CF8CC72BD916","edmCountry":{"def":["europe"]},"edmLanguage":{"def":["en"]}},"europeanaCollectionName":["08502_Ag_EU_ATHENA_TheIsraelMuseum"]}}